{"assets":{"F56BECC22B6FC6FA01AAA6E3669F993B":{"type":"texture","index":0,"assetRequest":{"type":"slide","state":"contents","slide":"none"},"url":{"native":"assets\/FD48B7BE-E1D5-45B2-9F34-EEF5F9E7D4E3.pdf"},"width":1920,"height":1080},"C1CBE202835D24624CB6B1408128048D":{"type":"texture","index":1,"assetRequest":{"type":"slide","state":"contents","slide":"none"},"url":{"native":"assets\/FD48B7BE-E1D5-45B2-9F34-EEF5F9E7D4E3.pdf"},"width":1920,"height":1080}},"events":[{"effects":[{"beginTime":0,"baseLayer":{"animations":[],"initialState":{"affineTransform":[1,0,0,1,0,0],"masksToBounds":false,"rotation":0,"scale":1,"position":{"pointX":960,"pointY":540},"width":1920,"sublayerTransform":[1,0,0,0,0,1,0,0,0,0,1,0,0,0,0,1],"contentsRect":{"y":0,"x":0,"width":1,"height":1},"opacity":1,"edgeAntialiasingMask":251658240,"height":1080,"hidden":false,"anchorPoint":{"pointX":0.5,"pointY":0.5}},"objectID":"0","layers":[{"animations":[],"initialState":{"affineTransform":[1,0,0,1,0,0],"masksToBounds":false,"rotation":0,"scale":1,"position":{"pointX":960,"pointY":540},"width":1920,"sublayerTransform":[1,0,0,0,0,1,0,0,0,0,1,-0.00035007912466775983,0,0,0,1],"contentsRect":{"y":0,"x":0,"width":1,"height":1},"opacity":1,"edgeAntialiasingMask":251658240,"height":1080,"hidden":false,"anchorPoint":{"pointX":0.5,"pointY":0.5}},"layers":[{"animations":[],"layers":[],"texturedRectangle":{"isBackgroundTexture":false,"singleTextureOpacity":1,"textureType":0,"textBaseline":0,"textXHeight":0,"isVerticalText":false},"initialState":{"affineTransform":[1,0,0,1,0,0],"masksToBounds":false,"rotation":0,"scale":1,"position":{"pointX":960,"pointY":540},"width":1920,"sublayerTransform":[1,0,0,0,0,1,0,0,0,0,1,0,0,0,0,1],"contentsRect":{"y":0,"x":0,"width":1,"height":1},"opacity":1,"edgeAntialiasingMask":0,"height":1080,"hidden":false,"anchorPoint":{"pointX":0.5,"pointY":0.5}},"texture":"C1CBE202835D24624CB6B1408128048D"},{"animations":[{"timeOffset":0,"from":{"scalar":false},"beginTime":0,"repeatCount":0,"fillMode":"both","property":"hidden","autoreverses":false,"duration":0.01,"to":{"scalar":true}}],"layers":[],"texturedRectangle":{"isBackgroundTexture":false,"singleTextureOpacity":1,"textureType":0,"textBaseline":0,"textXHeight":0,"isVerticalText":false},"initialState":{"affineTransform":[1,0,0,1,0,0],"masksToBounds":false,"rotation":0,"scale":1,"position":{"pointX":960,"pointY":540},"width":1920,"sublayerTransform":[1,0,0,0,0,1,0,0,0,0,1,0,0,0,0,1],"contentsRect":{"y":0,"x":0,"width":1,"height":1},"opacity":1,"edgeAntialiasingMask":0,"height":1080,"hidden":false,"anchorPoint":{"pointX":0.5,"pointY":0.5}},"texture":"F56BECC22B6FC6FA01AAA6E3669F993B"}]}]},"effects":[],"duration":0.01,"type":"transition","name":"none","objectID":"0"}],"automaticPlay":false,"hyperlinks":[],"accessibility":[{"text":"1","targetRectangle":{"y":324.99999761581421,"x":628.1015625,"width":57.796875,"height":112}},{"text":"'","targetRectangle":{"y":391.00000286102295,"x":1409.6015625,"width":154.125,"height":447}},{"text":"3","targetRectangle":{"y":325.99999761581421,"x":946.1015625,"width":57.796875,"height":112}},{"text":"Implicitly ends at the end","targetRectangle":{"y":833.85998451709747,"x":1318.6600227355957,"width":442.68000000000006,"height":76.280029296875}},{"text":"s='","targetRectangle":{"y":391.00000286102295,"x":64.023448944091797,"width":462.375,"height":447}},{"text":"6","targetRectangle":{"y":325.99999761581421,"x":1393.1015625,"width":57.796875,"height":112}},{"text":"4","targetRectangle":{"y":325.99999761581421,"x":1090.1015625,"width":57.796875,"height":112}},{"text":"Strings","targetRectangle":{"y":63.385757446289062,"x":843.02495999999996,"width":233.95008000000007,"height":94}},{"text":"2","targetRectangle":{"y":325.99999761581421,"x":787.1015625,"width":57.796875,"height":112}},{"text":"5","targetRectangle":{"y":325.99999761581421,"x":1250.1015625,"width":57.796875,"height":112}},{"text":"Arthur","targetRectangle":{"y":391.00000286102295,"x":512.12503051757812,"width":924.75,"height":447}},{"text":"Implicitly starts at 0","targetRectangle":{"y":833.85998451709747,"x":166.70999813079834,"width":362.58000000000015,"height":76.280029296875}},{"text":"0","targetRectangle":{"y":325.99999761581421,"x":468.81640625,"width":57.796875,"height":112}},{"text":"s[:2] ==  'Ar' ","targetRectangle":{"y":850.00000095367432,"x":757.5683536529541,"width":433.4765625,"height":56}},{"text":"s[3:] == 'hur'","targetRectangle":{"y":906.00000095367432,"x":757.5683536529541,"width":404.578125,"height":56}}],"baseLayer":{"animations":[],"initialState":{"affineTransform":[1,0,0,1,0,0],"masksToBounds":false,"rotation":0,"scale":1,"position":{"pointX":960,"pointY":540},"width":1920,"sublayerTransform":[1,0,0,0,0,1,0,0,0,0,1,0,0,0,0,1],"contentsRect":{"y":0,"x":0,"width":1,"height":1},"opacity":1,"edgeAntialiasingMask":251658240,"height":1080,"hidden":false,"anchorPoint":{"pointX":0.5,"pointY":0.5}},"objectID":"0","layers":[{"animations":[],"initialState":{"affineTransform":[1,0,0,1,0,0],"masksToBounds":false,"rotation":0,"scale":1,"position":{"pointX":960,"pointY":540},"width":1920,"sublayerTransform":[1,0,0,0,0,1,0,0,0,0,1,-0.00035007912466775983,0,0,0,1],"contentsRect":{"y":0,"x":0,"width":1,"height":1},"opacity":1,"edgeAntialiasingMask":251658240,"height":1080,"hidden":false,"anchorPoint":{"pointX":0.5,"pointY":0.5}},"layers":[{"animations":[],"layers":[],"texturedRectangle":{"isBackgroundTexture":false,"singleTextureOpacity":1,"textureType":0,"textBaseline":0,"textXHeight":0,"isVerticalText":false},"initialState":{"affineTransform":[1,0,0,1,0,0],"masksToBounds":false,"rotation":0,"scale":1,"position":{"pointX":960,"pointY":540},"width":1920,"sublayerTransform":[1,0,0,0,0,1,0,0,0,0,1,0,0,0,0,1],"contentsRect":{"y":0,"x":0,"width":1,"height":1},"opacity":1,"edgeAntialiasingMask":0,"height":1080,"hidden":false,"anchorPoint":{"pointX":0.5,"pointY":0.5}},"texture":"F56BECC22B6FC6FA01AAA6E3669F993B"}]}]}}]}